OFFICIAL/rtl/alu.v
module alu(
    input logic [31:0] op1,
    input logic [31:0] op2,
    input logic [3:0] alu_control, //opcode is always 0 for this module
    output logic [0:31] low,
    output logic [0:31] high,
    output logic [0:31] out
); 
    logic [63:0] divmult_out;

    always_comb begin
        case(alu_control)
            default: begin end
            4'b0000: begin //MULT
                divmult_out = op1*op2;
                out = 0;
            end
            4'b1001: begin //MULTU
                divmult_out = $unsigned(op1)* $unsigned(op2);
                out = 0;
            end

            4'b1101: begin //DIV
                divmult_out[31:0] = op1/op2;
                divmult_out[63:32] = op1%op2; 
                out = 0; end

            4'b1100: begin //DIVU
                divmult_out[31:0] = ($unsigned(op1)) / ($unsigned(op2));
                divmult_out[63:32] = $unsigned(op1) % $unsigned(op2); 
                out = 0; end

            4'b0001: out = $unsigned(op1) + $unsigned(op2); //ADDU
            4'b0010: out = op1<op2; //Set on less than - SLT
            4'b0011: out = $unsigned(op1) < $unsigned(op2); //SLTU
            4'b0100: out = op1&op2;//AND
            4'b0101: out = (op1|op2); //OR
            4'b0110: out = (op1^op2); //XOR
            4'b0111: out= op1;//Load upper immediate (Lui) (ALU control should handle immediate --> Op1)
            4'b1000: out = op2 << op1; // SLL(V) Logical Shift left/(same as ASL))
            4'b1010: out = op2 >> op1; //SRL(V) Logical Shift right 
            4'b1011: out = $signed(op2) >>> op1; //arithmetic shift right SRA(V). Variable- shiftamount value pushed onto op1 if this is the case.
            4'b1110: out = $unsigned(op1) - $unsigned(op2); //SUBU
            
            
    endcase

    end
    assign low  = divmult_out[31:0];
    assign high = divmult_out[63:32];

endmodule

OFFICIAL/rtl/mips_cpu_harvard.v
module mips_cpu_harvard(
    input logic [31:0] data_readdata, 
    input logic [31:0] instr_readdata, 
    input logic clk, 
    input logic reset, 
    input logic clock_enable,
    
    output logic [31:0] register_v0, 
    output logic [31:0] instr_address, //this might need to be changed to instr_address to meet the specs 
    output logic [31:0] data_address, 
    output logic [31:0] data_writedata, 
    output logic active, 
    output logic data_read,
    output logic data_write
    

    //DEBUGGING
    //output logic [5:0] OP, 
    //output logic [5:0] reg_addrw,
    //output logic[31:0] reg_write,
    //output logic[31:0] reg_t0, 
    //output logic [31:0] reg_t1,
);

    logic[5:0] OP; 
    logic[5:0] funct;
    logic[31:0] op_1, op_2, jump_address, PC_next, reg_write, out, HI, LO, HI_m, LO_m;
    logic[5:0] reg_addr1, reg_addr2, reg_addrw; //reg_addrw;
    logic[4:0] shamt;
    logic[15:0] astart; 
    logic next_active; 
    logic reset_prev; 
    logic write_enable;
    logic shift; 
    logic[3:0] ALU_code;
    logic[2:0]  OP_tail;
    logic [1:0] funct_tail;
    logic[2:0] subtype;
    logic R_type, I_type, J_type; 
    logic [3:0] PC_upper; 
    logic [25:0] target; 
    logic MSB;
    logic[31:0] instr;
    logic shift_op2;

    
     
    reg signed [31:0] HI_reg, LO_reg; 

//decoder
    typedef enum logic[5:0] {
        R = 6'b0,
        ADDIU = 6'b001001,
        ANDI = 6'b001100,
        SLTI = 6'b 001010,
        SLTIU= 6'b001011,
        SW = 6'b101011,
        LW = 6'b100011,
        XORI = 6'b001110,
        BEQ = 6'b000100,
        LUI = 6'b001111,
        ORI = 6'b001101,
        J = 6'b000010,
        JAL = 6'b000011, 
        B0 = 6'b000001, 
        BLEZ = 6'b000110,
        BGTZ = 6'b000111,
        BNE = 6'b000101
    } t_OP; 

    typedef enum logic[5:0]{
        JR = 6'b001000,
        ADDU = 6'b100001,
        AND = 6'b100100,
        SLT = 6'b101010,
        SLTU = 6'b101011,
        SUBU = 6'b100011,
        XOR = 6'b100110,
        SLL = 6'b0,
        SLLV = 6'b000100,
        SRA = 6'b000011,
        SRAV = 6'b000111,
        SRL = 6'b000010,
        SRLV = 6'b000110,
        DIV = 6'b011010,
        DIVU = 6'b011011,
        OR = 6'b100101,
        MULT = 6'b011000,
        MULTU = 6'b011001,
        JALR = 6'b001001,
        MTHI = 6'b010001,
        MTLO = 6'b010011,
        MFHI = 6'b010000,
        MFLO = 6'b010010
    } t_funct; 

    typedef enum logic[2:0]{
        Branch = 3'b0, //this has further separation when it's J type, because the second half of the word is the target 
        Imm = 3'b001,
        Load = 3'b100,
        Store = 3'b101
    } sub_t;


    typedef enum logic[4:0]{
        BLTZAL = 5'b10000,
        BLTZ = 5'b0,
        BGEZ = 5'b00001,
        BGEZAL = 5'b10001
    }B0_t; 

// Instruction decoding and control signals 
    //correct the endianness
    assign instr = {instr_readdata[7:0], instr_readdata[15:8], instr_readdata[23:16], instr_readdata[31:24]};
    assign OP = instr[31:26]; 
    assign funct = instr[5:0];
    assign shift = (funct[5:3] == 3'b0) ? 1 : 0; 
    assign funct_tail = funct[1:0]; 
    assign OP_tail = OP[2:0]; 
    assign subtype = instr[31:29];
    assign PC_upper = instr_address[31:28];
    assign target = instr[25:0]; 
    assign shift_op2 = funct[2];
    

    assign R_type = (OP == R) ? 1:0;
    assign J_type = (OP == JAL || OP == J) ? 1:0; 
    assign I_type = (!J_type && !R_type) ? 1:0; 

    assign astart = instr[15:0]; 


// ALU control definition 
    always_comb begin 

        if (OP==R) begin 
            if (shift) begin 
                ALU_code = {2'b10, funct_tail}; 
            end
            else begin 
                case (funct)
                MULT: ALU_code = 4'b0000;
                ADDU: ALU_code = 4'b0001;
                SLT: ALU_code = 4'b0010;
                SLTU: ALU_code = 4'b0011;
                AND: ALU_code = 4'b0100;
                OR: ALU_code = 4'b0101;
                XOR: ALU_code = 4'b0110;
                SUBU: ALU_code = 4'b1110; 
                MULTU: ALU_code = 4'b1001;
                DIVU: ALU_code = 4'b1100;
                DIV: ALU_code = 4'b1101; 
                endcase
            end
            // here I need something for the R type operations not included in this definition
        end 
        else begin
            ALU_code = {1'b0, OP_tail}; 
        end 
    end 
    
            
        
    reg [31:0] reg_file [31:0]; // need to sign extend partial loads here or elsewhere? 


    assign reg_addr1 = instr[25:21]; 
    assign reg_addr2 = instr[20:16]; 
    assign reg_addrw = (OP == R) ? instr[15:11] : ((OP==B0 && (reg_addr2 == BGEZAL || reg_addr2 == BLTZAL)) || OP == JAL) ? 5'd31 : instr[20:16]; //which part of the instruction word determines the address to write depends on the type of instruction

    assign write_enable = 
    ((OP == R 
        && funct != JR 
        && funct != DIV && funct != DIVU 
        && funct != MTHI && funct != MTLO 
        && funct != MULT && funct != MULTU)
    || subtype == Imm
    || subtype == Load
    || OP == JAL
    || (OP == B0 
        && (reg_addr2 == BGEZAL || reg_addr2 == BLTZAL))) ? 1 : 0; // these are all the occasions in which a register from the register file will have to be written 

// register file reading 
    assign shamt = instr[10:6];
    assign op_1 = (OP == R && shift && !shift_op2) ? {27'b0, shamt} : reg_file[reg_addr1]; 
    assign op_2 = (OP==R) ? reg_file[reg_addr2] : (OP == ANDI  || OP==OR  || OP==XORI) ? {16'b0, astart}: {{16{astart[15]}}, astart}; 
    

    assign MSB = op_1[31];

    assign register_v0 = reg_file[2]; 
   // assign reg_t1 = reg_file[9];  //DEBUGGING
   // assign reg_t0 = reg_file[8];   // DEBUGGING






// full load/store instructions
always_comb begin 
    data_read = reset ? 0 : (OP == LW) ? 1: 0; // this has to be added to make sure this two bits are paralised during reset (since there can't be anything coming out of RAM)
    data_write = reset ? 0: (OP == SW) ? 1: 0; // not sure if I can do this 
    data_address = (op_1 + astart); 
end 


// idk if these are needed 
// save the previous reset for the initialisation of instr_address
    always_ff@(negedge clk) begin 
        reset_prev <= reset;
    end 

    always_ff @(posedge clk) begin 
        active <= next_active; 
    end // this means that probably some of the asserts will be wrong 

/**/

//instantiate the ALU

//ops 
    always_comb begin
        case(OP)
        LW: reg_write = data_readdata; 
        SW: data_writedata = op_1;
        JAL: reg_write = instr_address+4; 
        B0: begin 
            if (reg_addr2 == BGEZAL || reg_addr2 == BLTZAL) begin 
                reg_write = instr_address +4;
            end 
        end 
        LUI: reg_write = {astart, 16'b0};
        R: begin
            if (funct == JALR) begin 
                reg_write = instr_address + 4; 
            end 
            else if (funct == JR) begin 
            end 
            else if (funct == MFHI) begin 
                reg_write = HI_reg;
            end 
            else if (funct == MFLO) begin 
                reg_write = LO_reg; 
            end
            else begin 
                reg_write = out; //this will set it to out even when it's doing Multiplication or division but it should be fine because the write enable shouldn't be one (even though it0s not very elegant, see what to do about this)
            end 
        end 
        default: reg_write = out; //this heavily relies on the write enable being correct, should really address this in testing 
        endcase 
    end 

//HI/LO
always_ff @(posedge clk) begin 
    if(OP == R && (funct == MULT || funct == MULTU || funct == DIV || funct == DIVU)) begin // to this I will need to add the other hi and lo instructions (MFLO; MTLO and so on)
        HI_reg <= HI; 
        LO_reg <= LO; 
    end 
    else if (OP == R && funct == MTLO) begin 
        LO_reg <= op_1;
    end 
    else if (OP == R && funct == MTHI) begin 
        HI_reg <= op_1;
    end 
end




//save the register address as it will change as soon as the next instruction is brought up 




// PC counter  
// note i don't think that we need to update PC next on the negedge (it should be fine anyway)
    always_comb begin 

// reset vector                         Note: I'm assuming PC won't be reset to 0 but to the reset vector directly, check if this is right
        if (reset) begin 
            PC_next = 32'hBFC00000;
        end 
//R_type  
        else if (R_type) begin 
            if (funct == JR || funct == JALR ) begin 
                 PC_next = op_1;
            end 
            else begin 
                PC_next = instr_address+4; 
            end
        end 
//J_type
        else if (J_type) begin 
            //case(OP)
            PC_next = {PC_upper, target, 2'b00}; 
            //JAL: PC_next = {PC_upper, target, 2'b00};          
            //default: PC_next = PC +4; 
           // endcase
        end 
//I_type 
        else if (I_type) begin 
            case(subtype)
            Branch: begin 
                //4 branches with equal opcode, they can be differentiated by looking at the bits in the places corresponding to reg_addr2 (rs)
                if (OP == B0) begin 
                    if(((reg_addr2 == BGEZ || reg_addr2 == BGEZAL) && !MSB) || ((reg_addr2 == BLTZ || reg_addr2 == BLTZAL) && MSB)) begin  //associate functions and conditions 
                        PC_next = instr_address + (astart * 4);
                        //I moved the saving of the register to the ops file 
                    end 
                    else begin 
                        PC_next = instr_address +4; 
                    end 
                end 
                // all other I_type branches 
                else if ( ((OP == BEQ) && (op_1 == op_2)) || ((OP == BGTZ) && (op_1 > 0)) || ((OP == BLEZ) && (op_1 <= 0)) || ((OP == BNE) && (op_1 != op_2))) begin 
                    PC_next = instr_address + (astart * 4); 
                end
                else begin 
                    PC_next = instr_address +4;
                end
            end
            default: PC_next = instr_address +4; 
            endcase 
        end 
    end 
    
//ALU 



//sequential block to actually change the PC address (since instruction fetching is combinatorial the new address must be defined only when we actually want the new instruction ie at the beginning of a new cycle)
    always_ff @(posedge clk) begin 
        instr_address <= PC_next; 
    end 

    /* begin 
                if (reset == 0) begin
                    PC <= PC_next; 
                end 
                else begin 
                    PC <= 0; 
                end 
            end 
    */   
     // this is in case PC needs to be 0 when reset is high
    


//active control 
    always_comb begin
        next_active = reset ? 1: (instr_address == 0) ? 0: active;  // even though active should be high during reset we need to make sure that it only activates if reset is high for more than a cycle, see how to do that 
    end 


// in case active needs to be 0 during reset: 
 /*   if (reset) begin 
            next_active = 1; 
        end 
        else if (PC != 0) begin 
            next_active = active; 
        end 
        else begin 
            next_active = 0; 
        end */



//register file writing
// what is relevant here is what reg_write is (defined in the logic block)

    always_ff @(posedge clk)  begin
        //add clock enable statement 
        // add a condition so that, if reset is 1, reg_write is 0
        if (reset && clock_enable) begin  // same here, the fact that it needs to be high for a whole cycle must be enforced 
            int i; 
            for (i=0; i<32; i= i+1) begin 
                reg_file[i] <= 0; 
            end 
        end 
        
        if (write_enable && clock_enable) begin 
            reg_file[reg_addrw] <= reg_write; 
        end 
     
        // for the above example try reg_file[reg_addrw] = reg_file
        
    end 
    alu ALU(
        .op1(op_1), .op2(op_2), .alu_control(ALU_code), .low(LO), .high(HI), .out(out)
    );
endmodule

OFFICIAL/test/ROM.v
module ROM_module(
input logic[31:0] addr,



output logic[31:0]instruction
);
// ROM
reg [7:0] ROM_0 [0:255];
reg [7:0] ROM_RESET_V [3217031168:3217031168+200];

assign instruction[7:0] = ROM_RESET_V[addr];
assign instruction[15:8] = ROM_RESET_V[addr+1];
assign instruction[23:16] = ROM_RESET_V[addr+2];
assign instruction[31:24] = ROM_RESET_V[addr+3];


initial begin
    //$readmemh("instructions.mem", ROM_RESET_V,3217031168);
    $readmemh(ROM_INIT_FILE, ROM_RESET_V,3217031168);
    $display("Instruction = %h",ROM_RESET_V[32'hBFC00000]);
    $display("Instruction r = %h",ROM_RESET_V[3217031168]);
end


endmodule

OFFICIAL/test/CPU_tb.v
module CPU_tb(
    
);
    logic     clk;
    logic     reset;
    logic    active;
    logic [31:0] register_v0;

    /* New clock enable. See below. */
    logic     clock_enable;

    /* Combinatorial read access to instructions */
    logic[31:0]  instr_address;
    logic[31:0]   instr_readdata;

    /* Combinatorial read and single-cycle write access to instructions */
    logic[31:0]  data_address;
    logic        data_write;
    logic        data_read;
    logic[31:0]  data_writedata;
    logic[31:0]  data_readdata;
   // logic[31:0] dummy;



    

    initial begin
       clk = 0;
       repeat (100000) begin
            #1 clk = !clk;
        end 
    end
 
    initial begin
    $dumpfile("CPU_TB.vcd");
    $dumpvars(0, CPU_tb);

      /*  $display("ROM MODULE RESULTS:");
        instr_address = 32'hBFC00000;
        $display("ROM_RESET_VECTOR[%h] = %h ", instr_address, instr_readdata);
        #1
        instr_address = 3217031172;
        $display("ROM_RESET_VECTOR[%h] = %h ", instr_address, instr_readdata);
        #1
        instr_address = 3217031176;
        $display("ROM_RESET_VECTOR[%h] = %b ", instr_address, instr_readdata);
        #1
        instr_address = 3217031180;
        $display("ROM_RESET_VECTOR[%h] = %b ", instr_address, instr_readdata); */


        #1
        clock_enable = 1;
        reset = 1;

        $display("ROM MODULE RESULTS:");
        

        @(posedge clk);
        reset = 0;
        $display("CPU started");


        repeat (15) begin
            @(posedge clk)
            $display("REG_V0 = %d", register_v0);
            
        end 

        
        


    end

       ROM_module MEM(
        .addr(instr_address),
        .instruction(instr_readdata)
    );

    mips_cpu_harvard CPU(
        .instr_readdata(instr_readdata), .clk(clk), .reset(reset), .clock_enable(clock_enable),
        .register_v0(register_v0), .instr_address(instr_address), .data_address(data_address), .data_writedata(data_writedata), .active(active), 
        .data_readdata(data_readdata), .data_write(data_write)
    
    
    );


endmodule

OFFICIAL/CPU_TB.vcd
$date
	Fri Dec 10 16:52:52 2021
$end
$version
	Icarus Verilog
$end
$timescale
	1s
$end
$scope module CPU_tb $end
$var wire 32 ! register_v0 [31:0] $end
$var wire 32 " instr_readdata [31:0] $end
$var wire 32 # instr_address [31:0] $end
$var wire 32 $ data_writedata [31:0] $end
$var wire 1 % data_write $end
$var wire 32 & data_address [31:0] $end
$var wire 1 ' active $end
$var reg 1 ( clk $end
$var reg 1 ) clock_enable $end
$var reg 32 * data_readdata [31:0] $end
$var reg 1 + reset $end
$scope module CPU $end
$var wire 1 ( clk $end
$var wire 1 ) clock_enable $end
$var wire 32 , data_readdata [31:0] $end
$var wire 32 - register_v0 [31:0] $end
$var wire 1 + reset $end
$var wire 1 . write_enable $end
$var wire 26 / target [25:0] $end
$var wire 3 0 subtype [2:0] $end
$var wire 1 1 shift_op2 $end
$var wire 1 2 shift $end
$var wire 5 3 shamt [4:0] $end
$var wire 6 4 reg_addrw [5:0] $end
$var wire 6 5 reg_addr2 [5:0] $end
$var wire 6 6 reg_addr1 [5:0] $end
$var wire 32 7 out [31:0] $end
$var wire 32 8 op_2 [31:0] $end
$var wire 32 9 op_1 [31:0] $end
$var wire 32 : instr_readdata [31:0] $end
$var wire 32 ; instr [31:0] $end
$var wire 2 < funct_tail [1:0] $end
$var wire 6 = funct [5:0] $end
$var wire 16 > astart [15:0] $end
$var wire 1 ? R_type $end
$var wire 4 @ PC_upper [3:0] $end
$var wire 3 A OP_tail [2:0] $end
$var wire 6 B OP [5:0] $end
$var wire 1 C MSB $end
$var wire 32 D LO [31:0] $end
$var wire 1 E J_type $end
$var wire 1 F I_type $end
$var wire 32 G HI [31:0] $end
$var reg 4 H ALU_code [3:0] $end
$var reg 32 I HI_reg [31:0] $end
$var reg 32 J LO_reg [31:0] $end
$var reg 32 K PC_next [31:0] $end
$var reg 1 ' active $end
$var reg 32 L data_address [31:0] $end
$var reg 1 M data_read $end
$var reg 1 % data_write $end
$var reg 32 N data_writedata [31:0] $end
$var reg 32 O instr_address [31:0] $end
$var reg 1 P next_active $end
$var reg 32 Q reg_write [31:0] $end
$var reg 1 R reset_prev $end
$scope module ALU $end
$var wire 4 S alu_control [3:0] $end
$var wire 32 T op1 [31:0] $end
$var wire 32 U op2 [31:0] $end
$var wire 32 V low [0:31] $end
$var wire 32 W high [0:31] $end
$var reg 64 X divmult_out [63:0] $end
$var reg 32 Y out [0:31] $end
$upscope $end
$scope begin $unm_blk_41 $end
$var integer 32 Z i [31:0] $end
$upscope $end
$upscope $end
$scope module MEM $end
$var wire 32 [ addr [31:0] $end
$var wire 32 \ instruction [31:0] $end
$upscope $end
$upscope $end
$enddefinitions $end
#0
$dumpvars
bx \
bx [
b0 Z
bx Y
bx X
bx W
bx V
bx U
bx T
b0xxx S
xR
bx Q
xP
bx O
bx N
xM
bx L
bx K
bx J
bx I
b0xxx H
bx G
xF
xE
bx D
xC
bx B
bx A
bx @
x?
bx >
bx =
bx <
bx ;
bx :
bx 9
bx 8
bx 7
b0xxxxx 6
b0xxxxx 5
b0xxxxx 4
bx 3
x2
x1
bx 0
bx /
x.
bx -
bx ,
x+
bx *
x)
0(
x'
bx &
x%
bx $
bx #
bx "
bx !
$end
#1
b0 !
b0 -
1P
b10111111110000000000000000000000 K
0%
0M
b100000 Z
1+
1)
1(
#2
1R
0(
#3
b10111111110000000000000000000100 K
1.
1F
b100100011 Q
b100100011 7
b100100011 Y
b100100011 &
b100100011 L
0E
02
0?
b10000 4
b1 H
b1 S
0C
b1 A
b11 <
01
b100100011 8
b100100011 U
b0 9
b0 T
b1001 B
b1 0
b0 6
b10000 5
b100011 =
b100000000000100100011 /
b100100011 >
b100 3
b1011 @
b100100000100000000000100100011 ;
b100011000000010001000000100100 "
b100011000000010001000000100100 :
b100011000000010001000000100100 \
b10111111110000000000000000000000 #
b10111111110000000000000000000000 O
b10111111110000000000000000000000 [
1'
1P
0%
0M
b100000 Z
0+
1(
#4
0R
0(
#5
0.
12
b0 Q
b0 4
b111 H
b111 S
b0 7
b0 Y
b111 A
b1 <
b1 8
b1 U
b1 &
b1 L
b111 B
b0 0
b0 5
b0 3
b1 =
b1 /
b1 >
b10111111110000000000000000001000 K
b11100000000000000000000000001 ;
b1000000000000000000011100 "
b1000000000000000000011100 :
b1000000000000000000011100 \
b10111111110000000000000000000100 #
b10111111110000000000000000000100 O
b10111111110000000000000000000100 [
1(
#6
0(
#7
1.
0F
b10111111110000000000000000001100 K
02
b0 D
b0 V
b0 G
b0 W
1?
b0 X
b0 A
b10 4
b1 H
b1 S
b0 8
b0 U
b1000000100001 &
b1000000100001 L
b0 B
b100001 =
b1000000100001 /
b1000000100001 >
b1000000100001 ;
b100001000100000000000000000000 "
b100001000100000000000000000000 :
b100001000100000000000000000000 \
b10111111110000000000000000001000 #
b10111111110000000000000000001000 O
b10111111110000000000000000001000 [
1(
#8
0(
#9
x.
xF
xE
x2
bx D
bx V
bx G
bx W
x?
xC
bx X
bx A
bx 9
bx T
bx 8
bx U
b0xxxxx 4
bx <
x1
b0xxx H
b0xxx S
bx &
bx L
x%
xM
bx B
bx 0
b0xxxxx 6
b0xxxxx 5
bx =
bx /
bx >
bx 3
b10111111110000000000000000010000 K
bx ;
bx "
bx :
bx \
b10111111110000000000000000001100 #
b10111111110000000000000000001100 O
b10111111110000000000000000001100 [
1(
#10
0(
#11
b10111111110000000000000000010000 #
b10111111110000000000000000010000 O
b10111111110000000000000000010000 [
1(
