OFFICIAL/rtl/loadstore.v
module loadstore (
    input [31:0] op_1,
    input [15:0] astart,
    //input [31:0] data_address, //guarda in che formato è e che informazioni contiene
    input [31:0] read_data, 
    input [31:0] op_2,
    input clk,
    input [5:0] OP,
    input stall,
    
    output[31:0] data,
    output [31:0] data_address

);
    logic[1:0] byte_enable; 
    logic[1:0] word_address; 
    logic[7:0] byte0, byte1, byte2, byte3, op_2_b0, op_2_b1, op_2_b2, op_2_b3;
    logic [31:0] data_prev;
    logic stall_prev;
    logic [31:0] address; 
    logic [31:0] data_temp; 
    logic sign0, sign1, sign2, sign3;
    // what is actually accessed in memory+
    assign address = op_1 +{{16{astart[15]}}, astart}; 
    assign byte_enable = address[1:0]; // this will tell me what byte I have 
    assign data_address = {address[31:2], 2'b0}; //the effective aligned address is the specified address but made aligned, so with last two bits = 0. We can do this as we always move words so we need to tell the RAM the aligned address for all the instructions  
    assign byte0 = read_data[7:0];
    assign byte1 = read_data[15:8]; 
    assign byte2 = read_data[23:16];
    assign byte3 = read_data[31:24];
    assign op_2_b0 = op_2[31:24]; //big-endian
    assign op_2_b1 =op_2[23:16];
    assign op_2_b2 = op_2[15:8];
    assign op_2_b3 = op_2[7:0];
    assign sign0 = byte0[7];
    assign sign1 = byte1[7];
    assign sign2 = byte2[7];
    assign sign3 = byte3[7];
    

    typedef enum logic[5:0]{
        SW = 6'b101011,
        LW = 6'b100011,
        LB = 6'b100000,
        LBU = 6'b100100,
        LH = 6'b 100001,
        LHU = 6'b100101,
        SB = 6'b101000,
        SH = 6'b101001,
        LWL = 6'b100010,
        LWR = 6'b100110
    }t_ls_OP;

//loads
    always_comb begin 
        case (OP)
        LWL: begin 
            case (byte_enable) 
            0: data_temp = {byte0, byte1, byte2, byte3}; 
            1: data_temp = {byte1, byte2, byte3, op_2_b3};
            2: data_temp= {byte2, byte3, op_2_b2, op_2_b3};
            3: data_temp= {byte3, op_2_b1, op_2_b2, op_2_b3};
            endcase 
        end 
        LB: begin
            case(byte_enable)
            0: data_temp= {{24{sign0}},byte0};
            1: data_temp= {{24{sign1}}, byte1};
            2: data_temp= {{24{sign2}}, byte2};
            3: data_temp= {{24{sign3}}, byte3};
            endcase
        end 
        LBU: begin 
            case(byte_enable)
            0: data_temp= {24'b0,byte0};
            1: data_temp= {24'b0, byte1};
            2: data_temp= {24'b0, byte2};
            3: data_temp= {24'b0, byte3};
            endcase
        end 
        LWR: begin
            case(byte_enable)
            0: data_temp= {op_2_b0, op_2_b1, op_2_b2, byte0};
            1: data_temp= {op_2_b0, op_2_b1, byte0, byte1};
            2: data_temp= {op_2_b0, byte0, byte1, byte2};
            3: data_temp= {byte0, byte1, byte2, byte3}; 
            endcase
        end
        LW: data_temp= {byte0, byte1, byte2, byte3};
        LH: data_temp= {{16{sign2}}, byte2, byte3}; //non so quale metà della parola vada caricata
        LHU: data_temp={16'b0, byte2, byte3}; 
        endcase
    end

//stores
    always_comb begin 
        case(OP)
        SW: data_temp= {op_2_b3, op_2_b2, op_2_b1, op_2_b0};
        SB: begin 
            if (stall) begin
                case(byte_enable)
                    0: data_prev = {byte3, byte2, byte1, op_2_b3};
                    1: data_prev = {byte3, byte2, op_2_b3, byte0};
                    2: data_prev = {byte3, op_2_b3, byte1, byte0};
                    3: data_prev = {op_2_b3, byte2, byte1, byte0};
                endcase
            end
            else begin 
                data_temp= data_prev; //so that in the next cycle we will store the patchworked word 
            end
        end
        SH: begin 
            if (stall) begin
                data_prev = {op_2_b3, op_2_b2, byte1, byte0};
            end
            else begin 
                data_temp= data_prev;
            end 
        end
        endcase  
    end

    assign data = data_temp; //for some reason you can't bind wires within an always_comb statement 


endmodule

OFFICIAL/rtl/alu.v
module alu(
    input logic [31:0] op1,
    input logic [31:0] op2,
    input logic [3:0] alu_control, //opcode is always 0 for this module
    output logic [0:31] low,
    output logic [0:31] high,
    output logic [0:31] out
); 
    logic [63:0] divmult_out;

    always_comb begin
        case(alu_control)
            default: begin end
            4'b0000: begin //MULT
                divmult_out = op1*op2;
                out = 0;
            end
            4'b1001: begin //MULTU
                divmult_out = $unsigned(op1)* $unsigned(op2);
                out = 0;
            end

            4'b1101: begin //DIV
                divmult_out[31:0] = op1/op2;
                divmult_out[63:32] = op1%op2; 
                out = 0; end

            4'b1100: begin //DIVU
                divmult_out[31:0] = ($unsigned(op1)) / ($unsigned(op2));
                divmult_out[63:32] = $unsigned(op1) % $unsigned(op2); 
                out = 0; end

            4'b0001: out = $unsigned(op1) + $unsigned(op2); //ADDU
            4'b0010: out = op1<op2; //Set on less than - SLT
            4'b0011: out = $unsigned(op1) < $unsigned(op2); //SLTU
            4'b0100: out = op1&op2;//AND
            4'b0101: out = (op1|op2); //OR
            4'b0110: out = (op1^op2); //XOR
            4'b0111: out= op1;//Load upper immediate (Lui) (ALU control should handle immediate --> Op1)
            4'b1000: out = op2 << op1; // SLL(V) Logical Shift left/(same as ASL))
            4'b1010: out = op2 >> op1; //SRL(V) Logical Shift right 
            4'b1011: out = $signed(op2) >>> op1; //arithmetic shift right SRA(V). Variable- shiftamount value pushed onto op1 if this is the case.
            4'b1110: out = $unsigned(op1) - $unsigned(op2); //SUBU
            
            
    endcase

    end
    assign low  = divmult_out[31:0];
    assign high = divmult_out[63:32];

endmodule

OFFICIAL/rtl/mips_cpu_harvard.v
module mips_cpu_harvard(
    input logic [31:0] data_readdata, 
    input logic [31:0] instr_readdata, 
    input logic clk, 
    input logic reset, 
    input logic clock_enable,
    
    output logic [31:0] register_v0, 
    output logic [31:0] instr_address, //this might need to be changed to instr_address to meet the specs 
    output logic [31:0] data_address, 
    output logic [31:0] data_writedata, 
    output logic active, 
    output logic data_read,
    output logic data_write
    
);

    logic[5:0] OP; 
    logic[5:0] funct;
    logic[31:0] op_1, op_2, jump_address, PC_next, reg_write, out, HI, LO, HI_m, LO_m;
    logic[5:0] reg_addr1, reg_addr2, reg_addrw; 
    logic[15:0] astart; 
    logic next_active; 
    logic reset_prev; 
    logic write_enable;
    logic shift; 
    logic[3:0] ALU_code;
    logic[2:0]  OP_tail;
    logic [1:0] funct_tail;
    logic[2:0] subtype;
    logic R_type, I_type, J_type; 
    logic [3:0] PC_upper; 
    logic [25:0] target; 
    logic MSB;
    logic[31:0] instr, instr_address_next, destination, jump_to;
    logic shift_op2;
    logic[31:0] data;
    logic stall, stall_prev, jump, jump_now;
    logic [32:0] branch_to, sign_ext_offset, sign_ext_address;
    logic msb_offset;
    logic[17:0]offset;
    logic[4:0]shamt;
    
    
    
    
     
    reg signed [31:0] HI_reg, LO_reg; 

//decoder
    typedef enum logic[5:0] {
        R = 6'b0,
        ADDIU = 6'b001001,
        ANDI = 6'b001100,
        SLTI = 6'b 001010,
        SLTIU= 6'b001011,
        SW = 6'b101011, 
        LW = 6'b100011,
        XORI = 6'b001110,
        BEQ = 6'b000100,
        LUI = 6'b001111,
        ORI = 6'b001101,
        J = 6'b000010,
        JAL = 6'b000011, 
        B0 = 6'b000001, 
        BLEZ = 6'b000110,
        BGTZ = 6'b000111,
        BNE = 6'b000101,
        LB = 6'b100000,
        LBU = 6'b100100,
        LH = 6'b 100001,
        LHU = 6'b100101,
        SB = 6'b101000,
        SH = 6'b101001,
        LWL = 6'b100010,
        LWR = 6'b100110
    } t_OP; 

    typedef enum logic[5:0]{
        JR = 6'b001000,
        ADDU = 6'b100001,
        AND = 6'b100100,
        SLT = 6'b101010,
        SLTU = 6'b101011,
        SUBU = 6'b100011,
        XOR = 6'b100110,
        SLL = 6'b0,
        SLLV = 6'b000100,
        SRA = 6'b000011,
        SRAV = 6'b000111,
        SRL = 6'b000010,
        SRLV = 6'b000110,
        DIV = 6'b011010,
        DIVU = 6'b011011,
        OR = 6'b100101,
        MULT = 6'b011000,
        MULTU = 6'b011001,
        JALR = 6'b001001,
        MTHI = 6'b010001,
        MTLO = 6'b010011,
        MFHI = 6'b010000,
        MFLO = 6'b010010
    } t_funct; 

    typedef enum logic[2:0]{
        Branch = 3'b0, //this has further separation when it's J type, because the second half of the word is the target 
        Imm = 3'b001,
        Load = 3'b100,
        Store = 3'b101
    } sub_t;


    typedef enum logic[4:0]{
        BLTZAL = 5'b10000,
        BLTZ = 5'b0,
        BGEZ = 5'b00001,
        BGEZAL = 5'b10001
    }B0_t; 

// INSTRUCTION DECODER and CONTROL SIGNALS  
    assign instr = {instr_readdata[7:0], instr_readdata[15:8], instr_readdata[23:16], instr_readdata[31:24]};
    assign OP = instr[31:26]; 
    assign funct = instr[5:0];
    assign shift = (funct[5:3] == 3'b0) ? 1 : 0; 
    assign funct_tail = funct[1:0]; 
    assign OP_tail = OP[2:0]; 
    assign subtype = instr[31:29];
    assign instr_address_next = instr_address + 4; 
    assign PC_upper = instr_address_next[31:28];
    assign target = instr[25:0]; 
    assign shift_op2 = funct[2];
    

    assign R_type = (OP == R) ? 1:0;
    assign J_type = (OP == JAL || OP == J) ? 1:0; 
    assign I_type = (!J_type && !R_type) ? 1:0; 

    assign astart = instr[15:0]; 


// ALU_CONTROL  
    always_comb begin 

        if (OP==R) begin 
            if (shift) begin 
                ALU_code = {2'b10, funct_tail}; 
            end
            else begin 
                case (funct)
                MULT: ALU_code = 4'b0000;
                ADDU: ALU_code = 4'b0001;
                SLT: ALU_code = 4'b0010;
                SLTU: ALU_code = 4'b0011;
                AND: ALU_code = 4'b0100;
                OR: ALU_code = 4'b0101;
                XOR: ALU_code = 4'b0110;
                SUBU: ALU_code = 4'b1110; 
                MULTU: ALU_code = 4'b1001;
                DIVU: ALU_code = 4'b1100;
                DIV: ALU_code = 4'b1101; 
                endcase
            end
        end 
        else begin
            ALU_code = {1'b0, OP_tail}; 
        end 
    end 
    
            
//REG_FILE related DECODER
    reg [31:0] reg_file [31:0]; 
    assign reg_addr1 = instr[25:21]; 
    assign reg_addr2 = instr[20:16]; 
    assign reg_addrw = (OP == R) ? instr[15:11] : ((OP==B0 && (reg_addr2 == BGEZAL || reg_addr2 == BLTZAL)) || OP == JAL) ? 5'd31 : instr[20:16]; 

    assign write_enable = 
    ((OP == R 
        && funct != JR 
        && funct != DIV && funct != DIVU 
        && funct != MTHI && funct != MTLO 
        && funct != MULT && funct != MULTU)
    || subtype == Imm
    || subtype == Load
    || OP == JAL
    || (OP == B0 
        && (reg_addr2 == BGEZAL || reg_addr2 == BLTZAL))) ? 1 : 0; // these are all the occasions in which a register from the register file will have to be written 


    assign shamt = instr[10:6];
    assign op_1 = (OP == R && shift && !shift_op2) ? {27'b0, shamt} : reg_file[reg_addr1]; 
    assign op_2 = (OP==R || OP==BEQ || OP==BNE || OP == SW || OP == SH || OP == SB || OP == LW || OP == LHU || OP == LH || OP == LBU || OP == LB || OP == LWL || OP == LWR) ? reg_file[reg_addr2] :  (OP == XORI || OP == ORI || OP == ANDI) ? {16'b0, astart} : {{16{astart[15]}}, astart};  

    assign MSB = op_1[31];

    assign register_v0 = reg_file[2]; 



//MEMORY_INTERFACE_CONTROLS
always_comb begin 
    stall = (((OP == SB) || (OP == SH)) && !stall_prev) ? 1:0;
    
    data_read = reset ? 0 : ( ( (OP ==  LW) || ( (OP == SH || OP == SB )  && (stall  == 1) ) || (OP == LB) || (OP == LBU) || (OP == LWL) || (OP == LWR) || (OP == LH) || (OP == LHU) ) ? 1  :0 );

    data_write = reset ? 0: ((OP == SW || OP == SB || OP == SH) && !stall) ? 1: 0; 
end  
    
always_ff @(posedge clk) begin 
        stall_prev <= stall; 
end



//REG_WRITE_SELECTION
    always_comb begin
        case(OP)
        JAL: reg_write = instr_address_next+4; 
        B0: begin 
            if (reg_addr2 == BGEZAL || reg_addr2 == BLTZAL) begin 
                reg_write = instr_address_next +4;
            end 
        end
        LUI: reg_write = {astart, 16'b0}; 
        R: begin
            if (funct == JALR) begin 
                reg_write = instr_address_next + 4; 
            end 
            else if (funct == JR) begin 
            end 
            else if (funct == MFHI) begin 
                reg_write = HI_reg;
            end 
            else if (funct == MFLO) begin 
                reg_write = LO_reg; 
            end
            else begin 
                reg_write = out; 
            end 
        end 
        default: begin
            if (subtype == Load) begin 
                reg_write = data; 
            end 
            else if (subtype == Store) begin 
                data_writedata = data; 
            end 
            else begin 
                reg_write = out; //this heavily relies on write_enable to be correct
            end 
        end
        endcase 
    end 

//HI_REG and LO_REG
always_ff @(posedge clk) begin 
    if(OP == R && (funct == MULT || funct == MULTU || funct == DIV || funct == DIVU)) begin 
        HI_reg <= HI; 
        LO_reg <= LO; 
    end 
    else if (OP == R && funct == MTLO) begin 
        LO_reg <= op_1;
    end 
    else if (OP == R && funct == MTHI) begin 
        HI_reg <= op_1;
    end 
end



// PC_BLOCK

    assign offset = $signed(astart)*4;
    assign sign_ext_offset = {{15{offset[17]}}, offset}; 
    assign sign_ext_address = {1'b0, instr_address};


    always_comb begin 
                      
        if (reset) begin 
            PC_next = 32'hBFC00000; //reset address
            jump = 0; 
        end 
        else if (stall) begin 
            PC_next = instr_address; 
            if (jump_now == 1) begin 
                jump = 1; 
            end 
            else begin 
                jump = 0; 
            end 
        end 
        jump_to = (OP == R && ( funct == JR || funct == JALR)) ? op_1 : {PC_upper, target, 2'b00}; //address it needs to go to in case of a jump
        branch_to = sign_ext_address + sign_ext_offset +4;  //address it needs to go to in case of a jump and of met conditions 
        jump =  ((R_type && (funct == JR || funct == JALR))  // controls the jump, will instruct the PC to jump after the branch delay slot instruction is executed
                || J_type 
                || (OP == B0 && 
                    (((reg_addr2 == BGEZ || reg_addr2 == BGEZAL) && !MSB) 
                     || ((reg_addr2 == BLTZ || reg_addr2 == BLTZAL) && MSB)))
                || ((OP == BEQ) && (op_1 == op_2))
                || ((OP == BGTZ) && (op_1 > 0))  
                || ((OP == BNE) && (op_1 != op_2)) 
                || ((OP == BLEZ) && (op_1 <= 0))) ? 1 : 0; 

    end 
    

    always_ff @(posedge clk) begin 
        destination <= stall ? destination : (J_type || (R_type && (funct == JALR || funct == JR))) ? jump_to : branch_to[31:0];
        jump_now <= jump; //to enable the execution of instruction in the branch delay slot 
        if (jump_now && !stall && !reset) begin 
            instr_address <= destination; 
        end 
        else begin 
           instr_address <= (reset || stall ) ? PC_next : instr_address_next; //this ensures that, if reset is not kept high for a whole cycle, reset effectively has no effect
        end
    end 



//ACTIVE_RESET_CONTROL
    always_ff@(posedge clk) begin 
        reset_prev <= reset;
    end 

    always_ff @(posedge clk) begin 
        active <= reset ? 1 : (instr_address == 0) ? 0 : active; 
    end 


//REG_FILE WRITING 

    always_ff @(posedge clk)  begin
        
        if (reset) begin //set everything to 0
            int i; 
            for (i=0; i<32; i= i+1) begin 
                reg_file[i] <= 0; 
            end 
        end 
        
        else if (write_enable && clock_enable) begin 
            reg_file[reg_addrw] <= reg_write; 
        end 
     
        
    end 
    alu ALU(
        .op1(op_1), .op2(op_2), .alu_control(ALU_code), .low(LO), .high(HI), .out(out)
    );
    loadstore ls (
        .OP(OP), .op_1(op_1), .astart(astart), .data_address(data_address), .read_data(data_readdata), .op_2(op_2), .clk(clk), .stall(stall), .data(data)
    );
endmodule

OFFICIAL/rtl/RAM.v
module RAM_module(
input logic[31:0] addr,
input logic [31:0] data_in,
input data_read,
input data_write,


output logic[31:0]data_out
);

// RAM
reg [7:0] RAM [0:1000];
logic [7:0] byte0_in, byte1_in, byte2_in, byte3_in;
//parameter RAM_INIT_FILE = "";

assign byte0_in = data_in[7:0];
assign byte1_in = data_in[15:8];
assign byte2_in = data_in[23:16];
assign byte3_in = data_in[31:24];

assign data_out[7:0] = (data_read && !data_write) ? RAM[addr+0]:0; //make sure that the CPU won't do anything with data_out when it shouldn't as the value won't be right 
assign data_out[15:8] = (data_read && !data_write) ? RAM[addr+1]:0;
assign data_out[23:16] = (data_read && !data_write) ? RAM[addr+2]:0;
assign data_out[31:24] = (data_read && !data_write) ? RAM[addr+3]:0;

always_comb begin
    if(!data_read && data_write) begin
        RAM[addr] = byte0_in;
        RAM[addr+1] = byte1_in;
        RAM[addr+2] = byte2_in;
        RAM[addr+3] = byte3_in;
    end
end

// assign dummy = (!data_read && data_write) ? data_in[7:0] : dummy2;
// assign RAM[addr+1] = (!data_read && data_write) ? data_in[15:8] : RAM[addr+1];
// assign RAM[addr+2] = (!data_read && data_write) ? data_in[23:16] : RAM[addr+2];
// assign RAM[addr+3] = (!data_read && data_write) ? data_in[31:24] : RAM[addr+3];




initial begin
    $readmemh("data.mem", RAM, 256, 1000);
    //$readmemh(RAM_INIT_FILE, RAM, 0);
end


endmodule

OFFICIAL/test/ROM.v
module ROM_module(
input logic[31:0] addr,



output logic[31:0]instruction
);
// ROM
reg [7:0] ROM_0 [0:255];
reg [7:0] ROM_RESET_V [3217031168:3217031168+200];

assign instruction[7:0] = ROM_RESET_V[addr];
assign instruction[15:8] = ROM_RESET_V[addr+1];
assign instruction[23:16] = ROM_RESET_V[addr+2];
assign instruction[31:24] = ROM_RESET_V[addr+3];


initial begin
    //$readmemh("instructions.mem", ROM_RESET_V,3217031168);
    $readmemh(ROM_INIT_FILE, ROM_RESET_V,3217031168);
    $display("Instruction = %h",ROM_RESET_V[32'hBFC00000]);
    $display("Instruction r = %h",ROM_RESET_V[3217031168]);
end


endmodule

OFFICIAL/test/CPU_tb.v
module CPU_tb(
    
);
    logic     clk;
    logic     reset;
    logic    active;
    logic [31:0] register_v0;

    /* New clock enable. See below. */
    logic     clock_enable;

    /* Combinatorial read access to instructions */
    logic[31:0]  instr_address;
    logic[31:0]   instr_readdata;

    /* Combinatorial read and single-cycle write access to instructions */
    logic[31:0]  data_address;
    logic        data_write;
    logic        data_read;
    logic[31:0]  data_writedata;
    logic[31:0]  data_readdata;
   // logic[31:0] dummy;

    //parameter RAM_INIT_FILE = "test/01-binary/countdown.hex";
    parameter ROM_INIT_FILE = "test/01-binary/countdown.hex";


    

    initial begin
       clk = 0;
       repeat (100000) begin
            #1 clk = !clk;
        end 
    end
 
    initial begin
    $dumpfile("CPU_TB.vcd");
    $dumpvars(0, CPU_tb);

      /*  $display("ROM MODULE RESULTS:");
        instr_address = 32'hBFC00000;
        $display("ROM_RESET_VECTOR[%h] = %h ", instr_address, instr_readdata);
        #1
        instr_address = 3217031172;
        $display("ROM_RESET_VECTOR[%h] = %h ", instr_address, instr_readdata);
        #1
        instr_address = 3217031176;
        $display("ROM_RESET_VECTOR[%h] = %b ", instr_address, instr_readdata);
        #1
        instr_address = 3217031180;
        $display("ROM_RESET_VECTOR[%h] = %b ", instr_address, instr_readdata); */


        #1
        clock_enable = 1;
        reset = 1;

        $display("ROM MODULE RESULTS:");
        

        @(posedge clk);
        reset = 0;
        $display("CPU started");


        repeat (15) begin
            @(posedge clk)
            $display("REG_V0 = %d", register_v0);
            
        end 

        
        


    end

       ROM_module #(ROM_INIT_FILE) MEM(
        .addr(instr_address),
        .instruction(instr_readdata)
    );


    RAM_module  ramx(
    .addr(data_address), 
    .data_in(data_writedata),
    .data_read(data_read),
    .data_write(data_write),
    .data_out(data_readdata)
    );

    mips_cpu_harvard CPU(
        .instr_readdata(instr_readdata), .clk(clk), .reset(reset), .clock_enable(clock_enable),
        .register_v0(register_v0), .instr_address(instr_address), .data_address(data_address), .data_writedata(data_writedata), .active(active), 
        .data_readdata(data_readdata), .data_write(data_write), .data_read(data_read)
    
    
    );


endmodule

OFFICIAL/CPU_TB.vcd
$date
	Tue Dec 14 16:23:03 2021
$end
$version
	Icarus Verilog
$end
$timescale
	1s
$end
$scope module CPU_tb $end
$var wire 32 ! register_v0 [31:0] $end
$var wire 32 " instr_readdata [31:0] $end
$var wire 32 # instr_address [31:0] $end
$var wire 32 $ data_writedata [31:0] $end
$var wire 1 % data_write $end
$var wire 32 & data_readdata [31:0] $end
$var wire 1 ' data_read $end
$var wire 32 ( data_address [31:0] $end
$var wire 1 ) active $end
$var reg 1 * clk $end
$var reg 1 + clock_enable $end
$var reg 1 , reset $end
$scope module CPU $end
$var wire 1 * clk $end
$var wire 1 + clock_enable $end
$var wire 32 - register_v0 [31:0] $end
$var wire 1 , reset $end
$var wire 1 . write_enable $end
$var wire 26 / target [25:0] $end
$var wire 3 0 subtype [2:0] $end
$var wire 33 1 sign_ext_offset [32:0] $end
$var wire 33 2 sign_ext_address [32:0] $end
$var wire 1 3 shift_op2 $end
$var wire 1 4 shift $end
$var wire 5 5 shamt [4:0] $end
$var wire 6 6 reg_addrw [5:0] $end
$var wire 6 7 reg_addr2 [5:0] $end
$var wire 6 8 reg_addr1 [5:0] $end
$var wire 32 9 out [31:0] $end
$var wire 32 : op_2 [31:0] $end
$var wire 32 ; op_1 [31:0] $end
$var wire 18 < offset [17:0] $end
$var wire 32 = instr_readdata [31:0] $end
$var wire 32 > instr_address_next [31:0] $end
$var wire 32 ? instr [31:0] $end
$var wire 2 @ funct_tail [1:0] $end
$var wire 6 A funct [5:0] $end
$var wire 32 B data_readdata [31:0] $end
$var wire 32 C data_address [31:0] $end
$var wire 32 D data [31:0] $end
$var wire 16 E astart [15:0] $end
$var wire 1 F R_type $end
$var wire 4 G PC_upper [3:0] $end
$var wire 3 H OP_tail [2:0] $end
$var wire 6 I OP [5:0] $end
$var wire 1 J MSB $end
$var wire 32 K LO [31:0] $end
$var wire 1 L J_type $end
$var wire 1 M I_type $end
$var wire 32 N HI [31:0] $end
$var reg 4 O ALU_code [3:0] $end
$var reg 32 P HI_reg [31:0] $end
$var reg 32 Q LO_reg [31:0] $end
$var reg 32 R PC_next [31:0] $end
$var reg 1 ) active $end
$var reg 33 S branch_to [32:0] $end
$var reg 1 ' data_read $end
$var reg 1 % data_write $end
$var reg 32 T data_writedata [31:0] $end
$var reg 32 U destination [31:0] $end
$var reg 32 V instr_address [31:0] $end
$var reg 1 W jump $end
$var reg 1 X jump_now $end
$var reg 32 Y jump_to [31:0] $end
$var reg 1 Z next_active $end
$var reg 32 [ reg_write [31:0] $end
$var reg 1 \ reset_prev $end
$var reg 1 ] stall $end
$var reg 1 ^ stall_prev $end
$scope module ALU $end
$var wire 4 _ alu_control [3:0] $end
$var wire 32 ` op1 [31:0] $end
$var wire 32 a op2 [31:0] $end
$var wire 32 b low [0:31] $end
$var wire 32 c high [0:31] $end
$var reg 64 d divmult_out [63:0] $end
$var reg 32 e out [0:31] $end
$upscope $end
$scope module ls $end
$var wire 6 f OP [5:0] $end
$var wire 16 g astart [15:0] $end
$var wire 1 * clk $end
$var wire 32 h data [31:0] $end
$var wire 32 i op_1 [31:0] $end
$var wire 32 j op_2 [31:0] $end
$var wire 1 ] stall $end
$var wire 1 k sign3 $end
$var wire 1 l sign2 $end
$var wire 1 m sign1 $end
$var wire 1 n sign0 $end
$var wire 32 o read_data [31:0] $end
$var wire 8 p op_2_b3 [7:0] $end
$var wire 8 q op_2_b2 [7:0] $end
$var wire 8 r op_2_b1 [7:0] $end
$var wire 8 s op_2_b0 [7:0] $end
$var wire 32 t data_address [31:0] $end
$var wire 2 u byte_enable [1:0] $end
$var wire 8 v byte3 [7:0] $end
$var wire 8 w byte2 [7:0] $end
$var wire 8 x byte1 [7:0] $end
$var wire 8 y byte0 [7:0] $end
$var wire 32 z address [31:0] $end
$var reg 32 { data_prev [31:0] $end
$var reg 32 | data_temp [31:0] $end
$upscope $end
$scope begin $unm_blk_41 $end
$var integer 32 } i [31:0] $end
$upscope $end
$upscope $end
$scope module MEM $end
$var wire 32 ~ addr [31:0] $end
$var wire 32 !" instruction [31:0] $end
$upscope $end
$scope module ramx $end
$var wire 32 "" addr [31:0] $end
$var wire 32 #" data_in [31:0] $end
$var wire 1 ' data_read $end
$var wire 1 % data_write $end
$var wire 32 $" data_out [31:0] $end
$var wire 8 %" byte3_in [7:0] $end
$var wire 8 &" byte2_in [7:0] $end
$var wire 8 '" byte1_in [7:0] $end
$var wire 8 (" byte0_in [7:0] $end
$upscope $end
$upscope $end
$enddefinitions $end
#0
$dumpvars
bx ("
bx '"
bx &"
bx %"
bx $"
bx #"
bx00 ""
bx !"
bx ~
b0 }
bx |
bx {
bx z
bx y
bx x
bx w
bx v
bx u
bx00 t
bx s
bx r
bx q
bx p
bx o
xn
xm
xl
xk
bx j
bx i
bx h
bx g
bx f
bx e
bx d
bx c
bx b
bx a
bx `
b0xxx _
x^
x]
x\
bx [
xZ
bx Y
xX
xW
bx V
bx U
bx T
bx S
bx R
bx Q
bx P
b0xxx O
bx N
xM
xL
bx K
xJ
bx I
bx H
bx G
xF
bx E
bx D
bx00 C
bx B
bx A
bx @
bx ?
bx >
bx =
bx <
bx ;
bx :
bx 9
b0xxxxx 8
b0xxxxx 7
b0xxxxx 6
bx 5
x4
x3
b0xxxxxxxxxxxxxxxxxxxxxxxxxxxxxxxx 2
bx 1
bx 0
bx /
x.
bx -
x,
x+
0*
x)
bx00 (
x'
bx &
x%
bx $
bx #
bx "
bx !
$end
#1
b0 !
b0 -
0n
0m
0l
0k
b0 y
b0 x
b0 w
b0 v
b0 &
b0 B
b0 o
b0 $"
1Z
xW
b10111111110000000000000000000000 R
0%
0'
b100000 }
1,
1+
1*
#2
1\
0*
#3
b11111111111111111111111111111111 [
b11111111 s
b11111111 r
b11111111 q
b11111111 p
b11111111111111111111111111111111 9
b11111111111111111111111111111111 e
b11111111111111111111111111111111 :
b11111111111111111111111111111111 a
b11111111111111111111111111111111 j
1.
1M
b11 u
b11111111111111111111111111111100 (
b11111111111111111111111111111100 C
b11111111111111111111111111111100 t
b11111111111111111111111111111100 ""
0W
0L
04
b11111111111111111111111111111111 z
0F
b10 6
0J
b1 O
b1 _
b10111111110000000000000000000000 S
b1 H
b11 @
13
b0 ;
b0 `
b0 i
0]
b10110000000010111111111111111100 Y
b1001 I
b1001 f
b1 0
b0 8
b10 7
b111111 A
b101111111111111111 /
b111111111111111111111111111111100 1
b111111111111111100 <
b1111111111111111 E
b1111111111111111 g
b11111 5
b1011 G
b100100000000101111111111111111 ?
b10111111110000000000000000000100 >
b10111111110000000000000000000000 2
b11111111111111110000001000100100 "
b11111111111111110000001000100100 =
b11111111111111110000001000100100 !"
b10111111110000000000000000000000 #
b10111111110000000000000000000000 V
b10111111110000000000000000000000 ~
1)
0n
0m
0l
0k
b0 y
b0 x
b0 w
b0 v
b0 &
b0 B
b0 o
b0 $"
1Z
0%
0'
b100000 }
0,
1*
#4
0\
0*
#5
0.
0M
b0 s
b0 r
1W
1F
b0 q
b0 p
b0 9
b0 e
b0 H
b0 6
b0 @
03
b0 :
b0 a
b0 j
b0 Y
b0 u
b1000 (
b1000 C
b1000 t
b1000 ""
b0 I
b0 f
b0 0
b0 7
b1000 A
b1000 /
b100000 1
b100000 <
b1000 z
b1000 E
b1000 g
b0 5
b1000 ?
b10111111110000000000000000101000 S
0^
b10111111110000000000000000001000 >
b10111111110000000000000000000100 2
b1000000000000000000000000000 "
b1000000000000000000000000000 =
b1000000000000000000000000000 !"
b10111111110000000000000000000100 #
b10111111110000000000000000000100 V
b10111111110000000000000000000100 ~
0X
b10111111110000000000000000000000 U
b11111111111111111111111111111111 !
b11111111111111111111111111111111 -
1*
#6
0*
#7
1.
1M
14
b0 9
b0 e
0F
1J
b0 s
b0 r
b0 q
b1 p
b1 K
b1 b
b0 N
b0 c
b1 H
b10 6
b11111111111111111111111111111111 ;
b11111111111111111111111111111111 `
b11111111111111111111111111111111 i
b1 :
b1 a
b1 j
b1 @
0W
b10110001000010000000000000000100 Y
b0 u
b0 (
b0 C
b0 t
b0 ""
b1 d
b1 O
b1 _
b0 [
b1001 I
b1001 f
b1 0
b10 8
b10 7
b1 A
b10000100000000000000001 /
b100 1
b100 <
b0 z
b1 E
b1 g
b100100010000100000000000000001 ?
b10111111110000000000000000010000 S
b10111111110000000000000000001100 >
b10111111110000000000000000001000 2
b1000000000100001000100100 "
b1000000000100001000100100 =
b1000000000100001000100100 !"
b10111111110000000000000000001000 #
b10111111110000000000000000001000 V
b10111111110000000000000000001000 ~
1X
b0 U
1*
#8
0*
#9
x.
xM
xn
xm
xl
xk
bx y
bx x
bx w
bx v
xL
x4
bx s
bx r
bx &
bx B
bx o
bx $"
xF
bx q
bx p
b0xxx O
b0xxx _
bx H
b0xxxxx 6
bx @
x3
bx :
bx a
bx j
bx00 (
bx00 C
bx00 t
bx00 ""
x%
x'
x]
xW
bx Y
bx I
bx f
bx 0
b0xxxxx 8
b0xxxxx 7
bx A
bx /
bx 1
bx <
bx E
bx g
bx 5
bx [
xJ
bx u
0Z
b0 G
bx ?
bx 9
bx e
bx S
bx z
bx ;
bx `
bx i
b100 >
b0 2
bx "
bx =
bx !"
b0 #
b0 V
b0 ~
0X
b10111111110000000000000000010000 U
b0 !
b0 -
1*
#10
0*
#11
bx G
bx >
b0x0xxxxxxxx0000000000000000000x00 2
bx0xxxxxxxx0000000000000000000x00 #
bx0xxxxxxxx0000000000000000000x00 V
bx0xxxxxxxx0000000000000000000x00 ~
xX
bx U
0)
x^
1*
#12
0*
#13
b0xxxxxxxxxxxxxxxxxxxxxxxxxxxxxxxx 2
bx #
bx V
bx ~
1*
